[
    {
        "trip_type": "FLIGHT",
        "date": "2023-12-05",
        "departure": "Oruro",
        "destination": "Cochabamba",
        "cost": 554,
        "reservation_type": "TripReservation"
    },
    {
        "checkin_date": "2023-12-05",
        "checkout_date": "2023-12-15",
        "hotel_name": "El Lucero",
        "city": "Oruro",
        "cost": 990,
        "reservation_type": "HotelReservation"
    },
    {
        "reservation_time": "2023-12-07T20:00:00",
        "restaurant": "Gustu",
        "city": "La Paz",
        "dish": "not specified",
        "cost": 29,
        "reservation_type": "RestaurantReservation"
    },
    {
        "trip_type": "FLIGHT",
        "date": "2024-01-02",
        "departure": "Cochabamba",
        "destination": "Dallas",
        "cost": 401,
        "reservation_type": "TripReservation"
    },
    {
        "reservation_time": "2024-10-19T10:00:00",
        "restaurant": "Texas",
        "city": "La Paz",
        "dish": "not specified",
        "cost": 457,
        "reservation_type": "RestaurantReservation"
    },
    {
        "reservation_time": "2024-10-20T10:00:00",
        "restaurant": "Texas",
        "city": "La Paz",
        "dish": "alitas",
        "cost": 337,
        "reservation_type": "RestaurantReservation"
    },
    {
        "checkin_date": "2023-12-05",
        "checkout_date": "2023-12-15",
        "hotel_name": "El Lucero",
        "city": "Oruro",
        "cost": 875,
        "reservation_type": "HotelReservation"
    },
    {
        "checkin_date": "2024-10-20",
        "checkout_date": "2024-10-30",
        "hotel_name": "Viru Viru",
        "city": "Santa Cruz",
        "cost": 775,
        "reservation_type": "HotelReservation"
    },
    {
        "trip_type": "FLIGHT",
        "date": "2024-10-31",
        "departure": "La Paz",
        "destination": "Santa Cruz",
        "cost": 202,
        "reservation_type": "TripReservation"
    },
    {
        "trip_type": "BUS",
        "date": "2024-11-01",
        "departure": "Santa Cruz",
        "destination": "La Paz",
        "cost": 81,
        "reservation_type": "TripReservation"
    },
    {
        "checkin_date": "2024-10-20",
        "checkout_date": "2024-10-22",
        "hotel_name": "Presidente",
        "city": "La Paz",
        "cost": 702,
        "reservation_type": "HotelReservation"
    }
]